dgrmr.py
setup.py
dgrmr.egg-info/PKG-INFO
dgrmr.egg-info/SOURCES.txt
dgrmr.egg-info/dependency_links.txt
dgrmr.egg-info/top_level.txt