Metadata-Version: 1.0
Name: dgrmr
Version: 0.1
Summary: Python data manipulation.
Home-page: UNKNOWN
Author: Peter Woyzbun
Author-email: peter.woyzbun@gmail.com
License: MIT
Platform: UNKNOWN
